nbconvert_styles/__init__.py
nbconvert_styles/KULeuven/KUL.png
nbconvert_styles/KULeuven/KULeuven.css
nbconvert_styles/KULeuven/KULeuven.png
nbconvert_styles/KULeuven/LICENSING
nbconvert_styles/KULeuven/base.html.j2
nbconvert_styles/KULeuven/conf.json
nbconvert_styles/KULeuven/index.html.j2
nbconvert_styles/KULeuven/sedes-sde.png
nbconvert_styles/KULeuven/sedes.png
nbconvert_styles/KULeuven/sleutel.png
jupyter_KULeuven_slides-0.3.5.dist-info/LICENSE
jupyter_KULeuven_slides-0.3.5.dist-info/METADATA
jupyter_KULeuven_slides-0.3.5.dist-info/WHEEL
jupyter_KULeuven_slides-0.3.5.dist-info/entry_points.txt
jupyter_KULeuven_slides-0.3.5.dist-info/top_level.txt
jupyter_KULeuven_slides-0.3.5.dist-info/RECORD
