Metadata-Version: 2.1
Name: jupyter-KULeuven-slides
Version: 0.3.5
Summary: A minimal and pip-installable jupyter nbconvert template for KULeuven slides.
Author-email: Jan Genoe <jan.genoe@kuleuven.be>
License: MIT
Keywords: jupyter,KULeuven,slides
Classifier: Framework :: Jupyter
Classifier: Intended Audience :: Science/Research
Classifier: Intended Audience :: Education
Classifier: Programming Language :: Python :: 3
Classifier: Programming Language :: Python :: 3.8
Classifier: Programming Language :: Python :: 3.9
Classifier: Programming Language :: Python :: 3.10
Classifier: Programming Language :: Python :: 3.11
Classifier: Programming Language :: Python :: 3.12
Classifier: License :: OSI Approved :: MIT License
Classifier: Operating System :: OS Independent
Requires-Python: >=3.8
License-File: LICENSE
Requires-Dist: jinja2 >=3.0
Requires-Dist: nbconvert >=7.2.5
